<?xml version="1.0" encoding="UTF-8"?>
<java version="18.0.1.1" class="java.beans.XMLDecoder">
 <object class="core.image.Entry" id="Entry0">
  <void property="dataFilament">
   <object class="core.cell.DataFilaments" id="DataFilaments0">
    <void property="filaments">
     <void method="add">
      <object class="core.filaments.CurvedFilament" id="CurvedFilament0">
       <void property="center">
        <object class="java.awt.Point" id="Point0">
         <void class="java.awt.Point" method="getField">
          <string>x</string>
          <void method="set">
           <object idref="Point0"/>
           <int>6466</int>
          </void>
         </void>
         <void class="java.awt.Point" method="getField">
          <string>y</string>
          <void method="set">
           <object idref="Point0"/>
           <int>9014</int>
          </void>
         </void>
        </object>
       </void>
       <void property="keep">
        <boolean>true</boolean>
       </void>
       <void property="length">
        <long>47044848</long>
       </void>
       <void property="number">
        <int>1</int>
       </void>
       <void property="orientation">
        <long>70016893</long>
       </void>
       <void property="points">
        <void method="add">
         <object class="java.awt.Point" id="Point1">
          <void class="java.awt.Point" method="getField">
           <string>x</string>
           <void method="set">
            <object idref="Point1"/>
            <int>640</int>
           </void>
          </void>
          <void class="java.awt.Point" method="getField">
           <string>y</string>
           <void method="set">
            <object idref="Point1"/>
            <int>924</int>
           </void>
          </void>
         </object>
        </void>
        <void method="add">
         <object class="java.awt.Point" id="Point2">
          <void class="java.awt.Point" method="getField">
           <string>x</string>
           <void method="set">
            <object idref="Point2"/>
            <int>649</int>
           </void>
          </void>
          <void class="java.awt.Point" method="getField">
           <string>y</string>
           <void method="set">
            <object idref="Point2"/>
            <int>893</int>
           </void>
          </void>
         </object>
        </void>
        <void method="add">
         <object class="java.awt.Point" id="Point3">
          <void class="java.awt.Point" method="getField">
           <string>x</string>
           <void method="set">
            <object idref="Point3"/>
            <int>656</int>
           </void>
          </void>
          <void class="java.awt.Point" method="getField">
           <string>y</string>
           <void method="set">
            <object idref="Point3"/>
            <int>880</int>
           </void>
          </void>
         </object>
        </void>
       </void>
       <void property="width">
        <long>4746787</long>
       </void>
      </object>
     </void>
     <void method="add">
      <object class="core.filaments.CurvedFilament" id="CurvedFilament1">
       <void property="center">
        <object class="java.awt.Point" id="Point4">
         <void class="java.awt.Point" method="getField">
          <string>x</string>
          <void method="set">
           <object idref="Point4"/>
           <int>6940</int>
          </void>
         </void>
         <void class="java.awt.Point" method="getField">
          <string>y</string>
          <void method="set">
           <object idref="Point4"/>
           <int>9030</int>
          </void>
         </void>
        </object>
       </void>
       <void property="keep">
        <boolean>true</boolean>
       </void>
       <void property="length">
        <long>40124735</long>
       </void>
       <void property="number">
        <int>2</int>
       </void>
       <void property="orientation">
        <long>91432096</long>
       </void>
       <void property="points">
        <void method="add">
         <object class="java.awt.Point" id="Point5">
          <void class="java.awt.Point" method="getField">
           <string>x</string>
           <void method="set">
            <object idref="Point5"/>
            <int>692</int>
           </void>
          </void>
          <void class="java.awt.Point" method="getField">
           <string>y</string>
           <void method="set">
            <object idref="Point5"/>
            <int>883</int>
           </void>
          </void>
         </object>
        </void>
        <void method="add">
         <object class="java.awt.Point" id="Point6">
          <void class="java.awt.Point" method="getField">
           <string>x</string>
           <void method="set">
            <object idref="Point6"/>
            <int>694</int>
           </void>
          </void>
          <void class="java.awt.Point" method="getField">
           <string>y</string>
           <void method="set">
            <object idref="Point6"/>
            <int>903</int>
           </void>
          </void>
         </object>
        </void>
        <void method="add">
         <object class="java.awt.Point" id="Point7">
          <void class="java.awt.Point" method="getField">
           <string>x</string>
           <void method="set">
            <object idref="Point7"/>
            <int>693</int>
           </void>
          </void>
          <void class="java.awt.Point" method="getField">
           <string>y</string>
           <void method="set">
            <object idref="Point7"/>
            <int>923</int>
           </void>
          </void>
         </object>
        </void>
       </void>
       <void property="width">
        <long>4907494</long>
       </void>
      </object>
     </void>
     <void method="add">
      <object class="core.filaments.CurvedFilament" id="CurvedFilament2">
       <void property="center">
        <object class="java.awt.Point" id="Point8">
         <void class="java.awt.Point" method="getField">
          <string>x</string>
          <void method="set">
           <object idref="Point8"/>
           <int>6650</int>
          </void>
         </void>
         <void class="java.awt.Point" method="getField">
          <string>y</string>
          <void method="set">
           <object idref="Point8"/>
           <int>9350</int>
          </void>
         </void>
        </object>
       </void>
       <void property="keep">
        <boolean>true</boolean>
       </void>
       <void property="length">
        <long>40124735</long>
       </void>
       <void property="number">
        <int>3</int>
       </void>
       <void property="orientation">
        <long>1432096</long>
       </void>
       <void property="points">
        <void method="add">
         <object class="java.awt.Point" id="Point9">
          <void class="java.awt.Point" method="getField">
           <string>x</string>
           <void method="set">
            <object idref="Point9"/>
            <int>685</int>
           </void>
          </void>
          <void class="java.awt.Point" method="getField">
           <string>y</string>
           <void method="set">
            <object idref="Point9"/>
            <int>933</int>
           </void>
          </void>
         </object>
        </void>
        <void method="add">
         <object class="java.awt.Point" id="Point10">
          <void class="java.awt.Point" method="getField">
           <string>x</string>
           <void method="set">
            <object idref="Point10"/>
            <int>665</int>
           </void>
          </void>
          <void class="java.awt.Point" method="getField">
           <string>y</string>
           <void method="set">
            <object idref="Point10"/>
            <int>935</int>
           </void>
          </void>
         </object>
        </void>
        <void method="add">
         <object class="java.awt.Point" id="Point11">
          <void class="java.awt.Point" method="getField">
           <string>x</string>
           <void method="set">
            <object idref="Point11"/>
            <int>645</int>
           </void>
          </void>
          <void class="java.awt.Point" method="getField">
           <string>y</string>
           <void method="set">
            <object idref="Point11"/>
            <int>934</int>
           </void>
          </void>
         </object>
        </void>
       </void>
       <void property="width">
        <long>5150695</long>
       </void>
      </object>
     </void>
     <void method="add">
      <object class="core.filaments.CurvedFilament" id="CurvedFilament3">
       <void property="center">
        <object class="java.awt.Point" id="Point12">
         <void class="java.awt.Point" method="getField">
          <string>x</string>
          <void method="set">
           <object idref="Point12"/>
           <int>6094</int>
          </void>
         </void>
         <void class="java.awt.Point" method="getField">
          <string>y</string>
          <void method="set">
           <object idref="Point12"/>
           <int>9636</int>
          </void>
         </void>
        </object>
       </void>
       <void property="keep">
        <boolean>true</boolean>
       </void>
       <void property="length">
        <long>67219518</long>
       </void>
       <void property="number">
        <int>4</int>
       </void>
       <void property="orientation">
        <long>56546691</long>
       </void>
       <void property="points">
        <void method="add">
         <object class="java.awt.Point" id="Point13">
          <void class="java.awt.Point" method="getField">
           <string>x</string>
           <void method="set">
            <object idref="Point13"/>
            <int>627</int>
           </void>
          </void>
          <void class="java.awt.Point" method="getField">
           <string>y</string>
           <void method="set">
            <object idref="Point13"/>
            <int>935</int>
           </void>
          </void>
         </object>
        </void>
        <void method="add">
         <object class="java.awt.Point" id="Point14">
          <void class="java.awt.Point" method="getField">
           <string>x</string>
           <void method="set">
            <object idref="Point14"/>
            <int>619</int>
           </void>
          </void>
          <void class="java.awt.Point" method="getField">
           <string>y</string>
           <void method="set">
            <object idref="Point14"/>
            <int>950</int>
           </void>
          </void>
         </object>
        </void>
        <void method="add">
         <object class="java.awt.Point" id="Point15">
          <void class="java.awt.Point" method="getField">
           <string>x</string>
           <void method="set">
            <object idref="Point15"/>
            <int>590</int>
           </void>
          </void>
          <void class="java.awt.Point" method="getField">
           <string>y</string>
           <void method="set">
            <object idref="Point15"/>
            <int>991</int>
           </void>
          </void>
         </object>
        </void>
       </void>
       <void property="width">
        <long>2861368</long>
       </void>
      </object>
     </void>
    </void>
   </object>
  </void>
  <void property="interiorContainer">
   <void property="interiorData">
    <array class="long" length="3">
     <void index="0">
      <long>42367</long>
     </void>
     <void index="1">
      <long>244527226</long>
     </void>
    </array>
   </void>
  </void>
  <void id="OrientationFieldContainer0" property="orientationFieldContainer">
   <void property="orientationFieldIds">
    <void method="add">
     <int>0</int>
    </void>
   </void>
   <void property="orientationFieldShapes">
    <array class="[I" length="1"/>
   </void>
   <void property="orientationFields">
    <array class="[[I" length="1">
     <void index="0">
      <array class="[I" length="129">
       <void index="0">
        <array class="int" length="3">
         <void index="0">
          <int>558</int>
         </void>
         <void index="1">
          <int>1012</int>
         </void>
         <void index="2">
          <int>-1</int>
         </void>
        </array>
       </void>
       <void index="1">
        <array class="int" length="3">
         <void index="0">
          <int>558</int>
         </void>
         <void index="1">
          <int>1025</int>
         </void>
         <void index="2">
          <int>-1</int>
         </void>
        </array>
       </void>
       <void index="2">
        <array class="int" length="3">
         <void index="0">
          <int>571</int>
         </void>
         <void index="1">
          <int>999</int>
         </void>
         <void index="2">
          <int>-1</int>
         </void>
        </array>
       </void>
       <void index="3">
        <array class="int" length="3">
         <void index="0">
          <int>571</int>
         </void>
         <void index="1">
          <int>1012</int>
         </void>
         <void index="2">
          <int>-1</int>
         </void>
        </array>
       </void>
       <void index="4">
        <array class="int" length="3">
         <void index="0">
          <int>571</int>
         </void>
         <void index="1">
          <int>1025</int>
         </void>
         <void index="2">
          <int>-1</int>
         </void>
        </array>
       </void>
       <void index="5">
        <array class="int" length="3">
         <void index="0">
          <int>584</int>
         </void>
         <void index="1">
          <int>908</int>
         </void>
         <void index="2">
          <int>-1</int>
         </void>
        </array>
       </void>
       <void index="6">
        <array class="int" length="3">
         <void index="0">
          <int>584</int>
         </void>
         <void index="1">
          <int>921</int>
         </void>
         <void index="2">
          <int>-1</int>
         </void>
        </array>
       </void>
       <void index="7">
        <array class="int" length="3">
         <void index="0">
          <int>584</int>
         </void>
         <void index="1">
          <int>986</int>
         </void>
         <void index="2">
          <int>-1</int>
         </void>
        </array>
       </void>
       <void index="8">
        <array class="int" length="3">
         <void index="0">
          <int>584</int>
         </void>
         <void index="1">
          <int>999</int>
         </void>
         <void index="2">
          <int>-1</int>
         </void>
        </array>
       </void>
       <void index="9">
        <array class="int" length="3">
         <void index="0">
          <int>584</int>
         </void>
         <void index="1">
          <int>1012</int>
         </void>
         <void index="2">
          <int>-1</int>
         </void>
        </array>
       </void>
       <void index="10">
        <array class="int" length="3">
         <void index="0">
          <int>597</int>
         </void>
         <void index="1">
          <int>908</int>
         </void>
         <void index="2">
          <int>-1</int>
         </void>
        </array>
       </void>
       <void index="11">
        <array class="int" length="3">
         <void index="0">
          <int>597</int>
         </void>
         <void index="1">
          <int>921</int>
         </void>
         <void index="2">
          <int>-1</int>
         </void>
        </array>
       </void>
       <void index="12">
        <array class="int" length="3">
         <void index="0">
          <int>597</int>
         </void>
         <void index="1">
          <int>973</int>
         </void>
         <void index="2">
          <int>-1</int>
         </void>
        </array>
       </void>
       <void index="13">
        <array class="int" length="3">
         <void index="0">
          <int>597</int>
         </void>
         <void index="1">
          <int>986</int>
         </void>
         <void index="2">
          <int>-1</int>
         </void>
        </array>
       </void>
       <void index="14">
        <array class="int" length="3">
         <void index="0">
          <int>597</int>
         </void>
         <void index="1">
          <int>999</int>
         </void>
         <void index="2">
          <int>-1</int>
         </void>
        </array>
       </void>
       <void index="15">
        <array class="int" length="3">
         <void index="0">
          <int>597</int>
         </void>
         <void index="1">
          <int>1012</int>
         </void>
         <void index="2">
          <int>-1</int>
         </void>
        </array>
       </void>
       <void index="16">
        <array class="int" length="3">
         <void index="0">
          <int>610</int>
         </void>
         <void index="1">
          <int>869</int>
         </void>
         <void index="2">
          <int>-1</int>
         </void>
        </array>
       </void>
       <void index="17">
        <array class="int" length="3">
         <void index="0">
          <int>610</int>
         </void>
         <void index="1">
          <int>882</int>
         </void>
         <void index="2">
          <int>-1</int>
         </void>
        </array>
       </void>
       <void index="18">
        <array class="int" length="3">
         <void index="0">
          <int>610</int>
         </void>
         <void index="1">
          <int>895</int>
         </void>
         <void index="2">
          <int>-1</int>
         </void>
        </array>
       </void>
       <void index="19">
        <array class="int" length="3">
         <void index="0">
          <int>610</int>
         </void>
         <void index="1">
          <int>908</int>
         </void>
         <void index="2">
          <int>-1</int>
         </void>
        </array>
       </void>
       <void index="20">
        <array class="int" length="3">
         <void index="0">
          <int>610</int>
         </void>
         <void index="1">
          <int>921</int>
         </void>
         <void index="2">
          <int>-1</int>
         </void>
        </array>
       </void>
       <void index="21">
        <array class="int" length="3">
         <void index="0">
          <int>610</int>
         </void>
         <void index="1">
          <int>934</int>
         </void>
         <void index="2">
          <int>-1</int>
         </void>
        </array>
       </void>
       <void index="22">
        <array class="int" length="3">
         <void index="0">
          <int>610</int>
         </void>
         <void index="1">
          <int>947</int>
         </void>
         <void index="2">
          <int>-1</int>
         </void>
        </array>
       </void>
       <void index="23">
        <array class="int" length="3">
         <void index="0">
          <int>610</int>
         </void>
         <void index="1">
          <int>960</int>
         </void>
         <void index="2">
          <int>-1</int>
         </void>
        </array>
       </void>
       <void index="24">
        <array class="int" length="3">
         <void index="0">
          <int>610</int>
         </void>
         <void index="1">
          <int>973</int>
         </void>
         <void index="2">
          <int>-1</int>
         </void>
        </array>
       </void>
       <void index="25">
        <array class="int" length="3">
         <void index="0">
          <int>610</int>
         </void>
         <void index="1">
          <int>986</int>
         </void>
         <void index="2">
          <int>-1</int>
         </void>
        </array>
       </void>
       <void index="26">
        <array class="int" length="3">
         <void index="0">
          <int>610</int>
         </void>
         <void index="1">
          <int>999</int>
         </void>
         <void index="2">
          <int>-1</int>
         </void>
        </array>
       </void>
       <void index="27">
        <array class="int" length="3">
         <void index="0">
          <int>623</int>
         </void>
         <void index="1">
          <int>843</int>
         </void>
         <void index="2">
          <int>-1</int>
         </void>
        </array>
       </void>
       <void index="28">
        <array class="int" length="3">
         <void index="0">
          <int>623</int>
         </void>
         <void index="1">
          <int>856</int>
         </void>
         <void index="2">
          <int>-1</int>
         </void>
        </array>
       </void>
       <void index="29">
        <array class="int" length="3">
         <void index="0">
          <int>623</int>
         </void>
         <void index="1">
          <int>869</int>
         </void>
         <void index="2">
          <int>-1</int>
         </void>
        </array>
       </void>
       <void index="30">
        <array class="int" length="3">
         <void index="0">
          <int>623</int>
         </void>
         <void index="1">
          <int>882</int>
         </void>
         <void index="2">
          <int>-1</int>
         </void>
        </array>
       </void>
       <void index="31">
        <array class="int" length="3">
         <void index="0">
          <int>623</int>
         </void>
         <void index="1">
          <int>895</int>
         </void>
         <void index="2">
          <int>-1</int>
         </void>
        </array>
       </void>
       <void index="32">
        <array class="int" length="3">
         <void index="0">
          <int>623</int>
         </void>
         <void index="1">
          <int>908</int>
         </void>
         <void index="2">
          <int>-1</int>
         </void>
        </array>
       </void>
       <void index="33">
        <array class="int" length="3">
         <void index="0">
          <int>623</int>
         </void>
         <void index="1">
          <int>921</int>
         </void>
         <void index="2">
          <int>-1</int>
         </void>
        </array>
       </void>
       <void index="34">
        <array class="int" length="3">
         <void index="0">
          <int>623</int>
         </void>
         <void index="1">
          <int>934</int>
         </void>
         <void index="2">
          <int>-1</int>
         </void>
        </array>
       </void>
       <void index="35">
        <array class="int" length="3">
         <void index="0">
          <int>623</int>
         </void>
         <void index="1">
          <int>947</int>
         </void>
         <void index="2">
          <int>-1</int>
         </void>
        </array>
       </void>
       <void index="36">
        <array class="int" length="3">
         <void index="0">
          <int>623</int>
         </void>
         <void index="1">
          <int>960</int>
         </void>
         <void index="2">
          <int>-1</int>
         </void>
        </array>
       </void>
       <void index="37">
        <array class="int" length="3">
         <void index="0">
          <int>623</int>
         </void>
         <void index="1">
          <int>973</int>
         </void>
         <void index="2">
          <int>-1</int>
         </void>
        </array>
       </void>
       <void index="38">
        <array class="int" length="3">
         <void index="0">
          <int>623</int>
         </void>
         <void index="1">
          <int>986</int>
         </void>
         <void index="2">
          <int>-1</int>
         </void>
        </array>
       </void>
       <void index="39">
        <array class="int" length="3">
         <void index="0">
          <int>623</int>
         </void>
         <void index="1">
          <int>999</int>
         </void>
         <void index="2">
          <int>-1</int>
         </void>
        </array>
       </void>
       <void index="40">
        <array class="int" length="3">
         <void index="0">
          <int>636</int>
         </void>
         <void index="1">
          <int>843</int>
         </void>
         <void index="2">
          <int>-1</int>
         </void>
        </array>
       </void>
       <void index="41">
        <array class="int" length="3">
         <void index="0">
          <int>636</int>
         </void>
         <void index="1">
          <int>856</int>
         </void>
         <void index="2">
          <int>-1</int>
         </void>
        </array>
       </void>
       <void index="42">
        <array class="int" length="3">
         <void index="0">
          <int>636</int>
         </void>
         <void index="1">
          <int>869</int>
         </void>
         <void index="2">
          <int>-1</int>
         </void>
        </array>
       </void>
       <void index="43">
        <array class="int" length="3">
         <void index="0">
          <int>636</int>
         </void>
         <void index="1">
          <int>882</int>
         </void>
         <void index="2">
          <int>-1</int>
         </void>
        </array>
       </void>
       <void index="44">
        <array class="int" length="3">
         <void index="0">
          <int>636</int>
         </void>
         <void index="1">
          <int>895</int>
         </void>
         <void index="2">
          <int>-1</int>
         </void>
        </array>
       </void>
       <void index="45">
        <array class="int" length="3">
         <void index="0">
          <int>636</int>
         </void>
         <void index="1">
          <int>908</int>
         </void>
         <void index="2">
          <int>-1</int>
         </void>
        </array>
       </void>
       <void index="46">
        <array class="int" length="3">
         <void index="0">
          <int>636</int>
         </void>
         <void index="1">
          <int>921</int>
         </void>
         <void index="2">
          <int>-1</int>
         </void>
        </array>
       </void>
       <void index="47">
        <array class="int" length="3">
         <void index="0">
          <int>636</int>
         </void>
         <void index="1">
          <int>934</int>
         </void>
         <void index="2">
          <int>-1</int>
         </void>
        </array>
       </void>
       <void index="48">
        <array class="int" length="3">
         <void index="0">
          <int>636</int>
         </void>
         <void index="1">
          <int>947</int>
         </void>
         <void index="2">
          <int>-1</int>
         </void>
        </array>
       </void>
       <void index="49">
        <array class="int" length="3">
         <void index="0">
          <int>636</int>
         </void>
         <void index="1">
          <int>960</int>
         </void>
         <void index="2">
          <int>-1</int>
         </void>
        </array>
       </void>
       <void index="50">
        <array class="int" length="3">
         <void index="0">
          <int>636</int>
         </void>
         <void index="1">
          <int>973</int>
         </void>
         <void index="2">
          <int>-1</int>
         </void>
        </array>
       </void>
       <void index="51">
        <array class="int" length="3">
         <void index="0">
          <int>636</int>
         </void>
         <void index="1">
          <int>986</int>
         </void>
         <void index="2">
          <int>-1</int>
         </void>
        </array>
       </void>
       <void index="52">
        <array class="int" length="3">
         <void index="0">
          <int>636</int>
         </void>
         <void index="1">
          <int>999</int>
         </void>
         <void index="2">
          <int>-1</int>
         </void>
        </array>
       </void>
       <void index="53">
        <array class="int" length="3">
         <void index="0">
          <int>636</int>
         </void>
         <void index="1">
          <int>1012</int>
         </void>
         <void index="2">
          <int>-1</int>
         </void>
        </array>
       </void>
       <void index="54">
        <array class="int" length="3">
         <void index="0">
          <int>649</int>
         </void>
         <void index="1">
          <int>843</int>
         </void>
         <void index="2">
          <int>-1</int>
         </void>
        </array>
       </void>
       <void index="55">
        <array class="int" length="3">
         <void index="0">
          <int>649</int>
         </void>
         <void index="1">
          <int>856</int>
         </void>
         <void index="2">
          <int>-1</int>
         </void>
        </array>
       </void>
       <void index="56">
        <array class="int" length="3">
         <void index="0">
          <int>649</int>
         </void>
         <void index="1">
          <int>869</int>
         </void>
         <void index="2">
          <int>-1</int>
         </void>
        </array>
       </void>
       <void index="57">
        <array class="int" length="3">
         <void index="0">
          <int>649</int>
         </void>
         <void index="1">
          <int>882</int>
         </void>
         <void index="2">
          <int>-1</int>
         </void>
        </array>
       </void>
       <void index="58">
        <array class="int" length="3">
         <void index="0">
          <int>649</int>
         </void>
         <void index="1">
          <int>895</int>
         </void>
         <void index="2">
          <int>-1</int>
         </void>
        </array>
       </void>
       <void index="59">
        <array class="int" length="3">
         <void index="0">
          <int>649</int>
         </void>
         <void index="1">
          <int>908</int>
         </void>
         <void index="2">
          <int>-1</int>
         </void>
        </array>
       </void>
       <void index="60">
        <array class="int" length="3">
         <void index="0">
          <int>649</int>
         </void>
         <void index="1">
          <int>921</int>
         </void>
         <void index="2">
          <int>-1</int>
         </void>
        </array>
       </void>
       <void index="61">
        <array class="int" length="3">
         <void index="0">
          <int>649</int>
         </void>
         <void index="1">
          <int>934</int>
         </void>
         <void index="2">
          <int>-1</int>
         </void>
        </array>
       </void>
       <void index="62">
        <array class="int" length="3">
         <void index="0">
          <int>649</int>
         </void>
         <void index="1">
          <int>947</int>
         </void>
         <void index="2">
          <int>-1</int>
         </void>
        </array>
       </void>
       <void index="63">
        <array class="int" length="3">
         <void index="0">
          <int>649</int>
         </void>
         <void index="1">
          <int>960</int>
         </void>
         <void index="2">
          <int>-1</int>
         </void>
        </array>
       </void>
       <void index="64">
        <array class="int" length="3">
         <void index="0">
          <int>649</int>
         </void>
         <void index="1">
          <int>973</int>
         </void>
         <void index="2">
          <int>-1</int>
         </void>
        </array>
       </void>
       <void index="65">
        <array class="int" length="3">
         <void index="0">
          <int>649</int>
         </void>
         <void index="1">
          <int>986</int>
         </void>
         <void index="2">
          <int>-1</int>
         </void>
        </array>
       </void>
       <void index="66">
        <array class="int" length="3">
         <void index="0">
          <int>649</int>
         </void>
         <void index="1">
          <int>999</int>
         </void>
         <void index="2">
          <int>-1</int>
         </void>
        </array>
       </void>
       <void index="67">
        <array class="int" length="3">
         <void index="0">
          <int>662</int>
         </void>
         <void index="1">
          <int>843</int>
         </void>
         <void index="2">
          <int>-1</int>
         </void>
        </array>
       </void>
       <void index="68">
        <array class="int" length="3">
         <void index="0">
          <int>662</int>
         </void>
         <void index="1">
          <int>856</int>
         </void>
         <void index="2">
          <int>-1</int>
         </void>
        </array>
       </void>
       <void index="69">
        <array class="int" length="3">
         <void index="0">
          <int>662</int>
         </void>
         <void index="1">
          <int>869</int>
         </void>
         <void index="2">
          <int>-1</int>
         </void>
        </array>
       </void>
       <void index="70">
        <array class="int" length="3">
         <void index="0">
          <int>662</int>
         </void>
         <void index="1">
          <int>882</int>
         </void>
         <void index="2">
          <int>-1</int>
         </void>
        </array>
       </void>
       <void index="71">
        <array class="int" length="3">
         <void index="0">
          <int>662</int>
         </void>
         <void index="1">
          <int>895</int>
         </void>
         <void index="2">
          <int>-1</int>
         </void>
        </array>
       </void>
       <void index="72">
        <array class="int" length="3">
         <void index="0">
          <int>662</int>
         </void>
         <void index="1">
          <int>908</int>
         </void>
         <void index="2">
          <int>-1</int>
         </void>
        </array>
       </void>
       <void index="73">
        <array class="int" length="3">
         <void index="0">
          <int>662</int>
         </void>
         <void index="1">
          <int>921</int>
         </void>
         <void index="2">
          <int>-1</int>
         </void>
        </array>
       </void>
       <void index="74">
        <array class="int" length="3">
         <void index="0">
          <int>662</int>
         </void>
         <void index="1">
          <int>934</int>
         </void>
         <void index="2">
          <int>-1</int>
         </void>
        </array>
       </void>
       <void index="75">
        <array class="int" length="3">
         <void index="0">
          <int>662</int>
         </void>
         <void index="1">
          <int>947</int>
         </void>
         <void index="2">
          <int>-1</int>
         </void>
        </array>
       </void>
       <void index="76">
        <array class="int" length="3">
         <void index="0">
          <int>662</int>
         </void>
         <void index="1">
          <int>960</int>
         </void>
         <void index="2">
          <int>-1</int>
         </void>
        </array>
       </void>
       <void index="77">
        <array class="int" length="3">
         <void index="0">
          <int>662</int>
         </void>
         <void index="1">
          <int>973</int>
         </void>
         <void index="2">
          <int>-1</int>
         </void>
        </array>
       </void>
       <void index="78">
        <array class="int" length="3">
         <void index="0">
          <int>675</int>
         </void>
         <void index="1">
          <int>843</int>
         </void>
         <void index="2">
          <int>-1</int>
         </void>
        </array>
       </void>
       <void index="79">
        <array class="int" length="3">
         <void index="0">
          <int>675</int>
         </void>
         <void index="1">
          <int>856</int>
         </void>
         <void index="2">
          <int>-1</int>
         </void>
        </array>
       </void>
       <void index="80">
        <array class="int" length="3">
         <void index="0">
          <int>675</int>
         </void>
         <void index="1">
          <int>869</int>
         </void>
         <void index="2">
          <int>-1</int>
         </void>
        </array>
       </void>
       <void index="81">
        <array class="int" length="3">
         <void index="0">
          <int>675</int>
         </void>
         <void index="1">
          <int>882</int>
         </void>
         <void index="2">
          <int>-1</int>
         </void>
        </array>
       </void>
       <void index="82">
        <array class="int" length="3">
         <void index="0">
          <int>675</int>
         </void>
         <void index="1">
          <int>895</int>
         </void>
         <void index="2">
          <int>-1</int>
         </void>
        </array>
       </void>
       <void index="83">
        <array class="int" length="3">
         <void index="0">
          <int>675</int>
         </void>
         <void index="1">
          <int>908</int>
         </void>
         <void index="2">
          <int>-1</int>
         </void>
        </array>
       </void>
       <void index="84">
        <array class="int" length="3">
         <void index="0">
          <int>675</int>
         </void>
         <void index="1">
          <int>921</int>
         </void>
         <void index="2">
          <int>-1</int>
         </void>
        </array>
       </void>
       <void index="85">
        <array class="int" length="3">
         <void index="0">
          <int>675</int>
         </void>
         <void index="1">
          <int>934</int>
         </void>
         <void index="2">
          <int>-1</int>
         </void>
        </array>
       </void>
       <void index="86">
        <array class="int" length="3">
         <void index="0">
          <int>675</int>
         </void>
         <void index="1">
          <int>947</int>
         </void>
         <void index="2">
          <int>-1</int>
         </void>
        </array>
       </void>
       <void index="87">
        <array class="int" length="3">
         <void index="0">
          <int>675</int>
         </void>
         <void index="1">
          <int>960</int>
         </void>
         <void index="2">
          <int>-1</int>
         </void>
        </array>
       </void>
       <void index="88">
        <array class="int" length="3">
         <void index="0">
          <int>675</int>
         </void>
         <void index="1">
          <int>973</int>
         </void>
         <void index="2">
          <int>-1</int>
         </void>
        </array>
       </void>
       <void index="89">
        <array class="int" length="3">
         <void index="0">
          <int>688</int>
         </void>
         <void index="1">
          <int>843</int>
         </void>
         <void index="2">
          <int>-1</int>
         </void>
        </array>
       </void>
       <void index="90">
        <array class="int" length="3">
         <void index="0">
          <int>688</int>
         </void>
         <void index="1">
          <int>856</int>
         </void>
         <void index="2">
          <int>-1</int>
         </void>
        </array>
       </void>
       <void index="91">
        <array class="int" length="3">
         <void index="0">
          <int>688</int>
         </void>
         <void index="1">
          <int>869</int>
         </void>
         <void index="2">
          <int>-1</int>
         </void>
        </array>
       </void>
       <void index="92">
        <array class="int" length="3">
         <void index="0">
          <int>688</int>
         </void>
         <void index="1">
          <int>882</int>
         </void>
         <void index="2">
          <int>-1</int>
         </void>
        </array>
       </void>
       <void index="93">
        <array class="int" length="3">
         <void index="0">
          <int>688</int>
         </void>
         <void index="1">
          <int>895</int>
         </void>
         <void index="2">
          <int>-1</int>
         </void>
        </array>
       </void>
       <void index="94">
        <array class="int" length="3">
         <void index="0">
          <int>688</int>
         </void>
         <void index="1">
          <int>908</int>
         </void>
         <void index="2">
          <int>-1</int>
         </void>
        </array>
       </void>
       <void index="95">
        <array class="int" length="3">
         <void index="0">
          <int>688</int>
         </void>
         <void index="1">
          <int>921</int>
         </void>
         <void index="2">
          <int>-1</int>
         </void>
        </array>
       </void>
       <void index="96">
        <array class="int" length="3">
         <void index="0">
          <int>688</int>
         </void>
         <void index="1">
          <int>934</int>
         </void>
         <void index="2">
          <int>-1</int>
         </void>
        </array>
       </void>
       <void index="97">
        <array class="int" length="3">
         <void index="0">
          <int>688</int>
         </void>
         <void index="1">
          <int>947</int>
         </void>
         <void index="2">
          <int>-1</int>
         </void>
        </array>
       </void>
       <void index="98">
        <array class="int" length="3">
         <void index="0">
          <int>688</int>
         </void>
         <void index="1">
          <int>960</int>
         </void>
         <void index="2">
          <int>-1</int>
         </void>
        </array>
       </void>
       <void index="99">
        <array class="int" length="3">
         <void index="0">
          <int>688</int>
         </void>
         <void index="1">
          <int>973</int>
         </void>
         <void index="2">
          <int>-1</int>
         </void>
        </array>
       </void>
       <void index="100">
        <array class="int" length="3">
         <void index="0">
          <int>701</int>
         </void>
         <void index="1">
          <int>856</int>
         </void>
         <void index="2">
          <int>-1</int>
         </void>
        </array>
       </void>
       <void index="101">
        <array class="int" length="3">
         <void index="0">
          <int>701</int>
         </void>
         <void index="1">
          <int>869</int>
         </void>
         <void index="2">
          <int>-1</int>
         </void>
        </array>
       </void>
       <void index="102">
        <array class="int" length="3">
         <void index="0">
          <int>701</int>
         </void>
         <void index="1">
          <int>882</int>
         </void>
         <void index="2">
          <int>-1</int>
         </void>
        </array>
       </void>
       <void index="103">
        <array class="int" length="3">
         <void index="0">
          <int>701</int>
         </void>
         <void index="1">
          <int>895</int>
         </void>
         <void index="2">
          <int>-1</int>
         </void>
        </array>
       </void>
       <void index="104">
        <array class="int" length="3">
         <void index="0">
          <int>701</int>
         </void>
         <void index="1">
          <int>908</int>
         </void>
         <void index="2">
          <int>-1</int>
         </void>
        </array>
       </void>
       <void index="105">
        <array class="int" length="3">
         <void index="0">
          <int>701</int>
         </void>
         <void index="1">
          <int>921</int>
         </void>
         <void index="2">
          <int>-1</int>
         </void>
        </array>
       </void>
       <void index="106">
        <array class="int" length="3">
         <void index="0">
          <int>701</int>
         </void>
         <void index="1">
          <int>934</int>
         </void>
         <void index="2">
          <int>-1</int>
         </void>
        </array>
       </void>
       <void index="107">
        <array class="int" length="3">
         <void index="0">
          <int>701</int>
         </void>
         <void index="1">
          <int>947</int>
         </void>
         <void index="2">
          <int>-1</int>
         </void>
        </array>
       </void>
       <void index="108">
        <array class="int" length="3">
         <void index="0">
          <int>701</int>
         </void>
         <void index="1">
          <int>960</int>
         </void>
         <void index="2">
          <int>-1</int>
         </void>
        </array>
       </void>
       <void index="109">
        <array class="int" length="3">
         <void index="0">
          <int>701</int>
         </void>
         <void index="1">
          <int>973</int>
         </void>
         <void index="2">
          <int>-1</int>
         </void>
        </array>
       </void>
       <void index="110">
        <array class="int" length="3">
         <void index="0">
          <int>714</int>
         </void>
         <void index="1">
          <int>856</int>
         </void>
         <void index="2">
          <int>-1</int>
         </void>
        </array>
       </void>
       <void index="111">
        <array class="int" length="3">
         <void index="0">
          <int>714</int>
         </void>
         <void index="1">
          <int>869</int>
         </void>
         <void index="2">
          <int>-1</int>
         </void>
        </array>
       </void>
       <void index="112">
        <array class="int" length="3">
         <void index="0">
          <int>714</int>
         </void>
         <void index="1">
          <int>882</int>
         </void>
         <void index="2">
          <int>-1</int>
         </void>
        </array>
       </void>
       <void index="113">
        <array class="int" length="3">
         <void index="0">
          <int>714</int>
         </void>
         <void index="1">
          <int>895</int>
         </void>
         <void index="2">
          <int>-1</int>
         </void>
        </array>
       </void>
       <void index="114">
        <array class="int" length="3">
         <void index="0">
          <int>714</int>
         </void>
         <void index="1">
          <int>908</int>
         </void>
         <void index="2">
          <int>-1</int>
         </void>
        </array>
       </void>
       <void index="115">
        <array class="int" length="3">
         <void index="0">
          <int>714</int>
         </void>
         <void index="1">
          <int>921</int>
         </void>
         <void index="2">
          <int>-1</int>
         </void>
        </array>
       </void>
       <void index="116">
        <array class="int" length="3">
         <void index="0">
          <int>714</int>
         </void>
         <void index="1">
          <int>934</int>
         </void>
         <void index="2">
          <int>-1</int>
         </void>
        </array>
       </void>
       <void index="117">
        <array class="int" length="3">
         <void index="0">
          <int>714</int>
         </void>
         <void index="1">
          <int>947</int>
         </void>
         <void index="2">
          <int>-1</int>
         </void>
        </array>
       </void>
       <void index="118">
        <array class="int" length="3">
         <void index="0">
          <int>714</int>
         </void>
         <void index="1">
          <int>960</int>
         </void>
         <void index="2">
          <int>-1</int>
         </void>
        </array>
       </void>
       <void index="119">
        <array class="int" length="3">
         <void index="0">
          <int>714</int>
         </void>
         <void index="1">
          <int>973</int>
         </void>
         <void index="2">
          <int>-1</int>
         </void>
        </array>
       </void>
       <void index="120">
        <array class="int" length="3">
         <void index="0">
          <int>727</int>
         </void>
         <void index="1">
          <int>856</int>
         </void>
         <void index="2">
          <int>-1</int>
         </void>
        </array>
       </void>
       <void index="121">
        <array class="int" length="3">
         <void index="0">
          <int>727</int>
         </void>
         <void index="1">
          <int>869</int>
         </void>
         <void index="2">
          <int>-1</int>
         </void>
        </array>
       </void>
       <void index="122">
        <array class="int" length="3">
         <void index="0">
          <int>727</int>
         </void>
         <void index="1">
          <int>882</int>
         </void>
         <void index="2">
          <int>-1</int>
         </void>
        </array>
       </void>
       <void index="123">
        <array class="int" length="3">
         <void index="0">
          <int>727</int>
         </void>
         <void index="1">
          <int>895</int>
         </void>
         <void index="2">
          <int>-1</int>
         </void>
        </array>
       </void>
       <void index="124">
        <array class="int" length="3">
         <void index="0">
          <int>727</int>
         </void>
         <void index="1">
          <int>908</int>
         </void>
         <void index="2">
          <int>-1</int>
         </void>
        </array>
       </void>
       <void index="125">
        <array class="int" length="3">
         <void index="0">
          <int>727</int>
         </void>
         <void index="1">
          <int>921</int>
         </void>
         <void index="2">
          <int>-1</int>
         </void>
        </array>
       </void>
       <void index="126">
        <array class="int" length="3">
         <void index="0">
          <int>727</int>
         </void>
         <void index="1">
          <int>934</int>
         </void>
         <void index="2">
          <int>-1</int>
         </void>
        </array>
       </void>
       <void index="127">
        <array class="int" length="3">
         <void index="0">
          <int>727</int>
         </void>
         <void index="1">
          <int>947</int>
         </void>
         <void index="2">
          <int>-1</int>
         </void>
        </array>
       </void>
       <void index="128">
        <array class="int" length="3">
         <void index="0">
          <int>727</int>
         </void>
         <void index="1">
          <int>960</int>
         </void>
         <void index="2">
          <int>-1</int>
         </void>
        </array>
       </void>
      </array>
     </void>
    </array>
   </void>
  </void>
  <void property="path">
   <string>/Users/ybok6692/USYD/ToMaCo/24hrs_hMSCs/part2/nucleus/116.tif</string>
  </void>
  <void property="shape">
   <object class="core.cell.ShapeContainer" id="ShapeContainer0">
    <void property="areas">
     <void method="add">
      <object class="core.cell.CellShape">
       <void property="area">
        <double>42367.0</double>
       </void>
       <void property="aspectRatio">
        <long>1040099</long>
       </void>
       <void property="bounds">
        <object class="java.awt.Rectangle" id="Rectangle0">
         <void class="java.awt.Rectangle" method="getField">
          <string>x</string>
          <void method="set">
           <object idref="Rectangle0"/>
           <int>571</int>
          </void>
         </void>
         <void class="java.awt.Rectangle" method="getField">
          <string>y</string>
          <void method="set">
           <object idref="Rectangle0"/>
           <int>718</int>
          </void>
         </void>
         <void class="java.awt.Rectangle" method="getField">
          <string>width</string>
          <void method="set">
           <object idref="Rectangle0"/>
           <int>357</int>
          </void>
         </void>
         <void class="java.awt.Rectangle" method="getField">
          <string>height</string>
          <void method="set">
           <object idref="Rectangle0"/>
           <int>294</int>
          </void>
         </void>
        </object>
       </void>
       <void property="center">
        <object class="java.awt.Point" id="Point16">
         <void class="java.awt.Point" method="getField">
          <string>x</string>
          <void method="set">
           <object idref="Point16"/>
           <int>332</int>
          </void>
         </void>
         <void class="java.awt.Point" method="getField">
          <string>y</string>
          <void method="set">
           <object idref="Point16"/>
           <int>521</int>
          </void>
         </void>
        </object>
       </void>
       <void property="excursion">
        <long>211225</long>
       </void>
       <void property="longHalfAxis">
        <long>118433962</long>
       </void>
       <void property="newOrderParameter">
        <long>533163</long>
       </void>
       <void property="newOrientation">
        <long>64090777</long>
       </void>
       <void property="orderParameter">
        <long>-430940</long>
       </void>
       <void property="orientation">
        <long>136054466</long>
       </void>
      </object>
     </void>
    </void>
    <void property="extAreas">
     <void method="add">
      <object class="core.cell.CellShape">
       <void property="area">
        <double>78112.0</double>
       </void>
       <void property="aspectRatio">
        <long>1091395</long>
       </void>
       <void property="bounds">
        <object class="java.awt.Rectangle" id="Rectangle1">
         <void class="java.awt.Rectangle" method="getField">
          <string>x</string>
          <void method="set">
           <object idref="Rectangle1"/>
           <int>424</int>
          </void>
         </void>
         <void class="java.awt.Rectangle" method="getField">
          <string>y</string>
          <void method="set">
           <object idref="Rectangle1"/>
           <int>615</int>
          </void>
         </void>
         <void class="java.awt.Rectangle" method="getField">
          <string>width</string>
          <void method="set">
           <object idref="Rectangle1"/>
           <int>573</int>
          </void>
         </void>
         <void class="java.awt.Rectangle" method="getField">
          <string>height</string>
          <void method="set">
           <object idref="Rectangle1"/>
           <int>530</int>
          </void>
         </void>
        </object>
       </void>
       <void property="center">
        <object class="java.awt.Point" id="Point17">
         <void class="java.awt.Point" method="getField">
          <string>x</string>
          <void method="set">
           <object idref="Point17"/>
           <int>320</int>
          </void>
         </void>
         <void class="java.awt.Point" method="getField">
          <string>y</string>
          <void method="set">
           <object idref="Point17"/>
           <int>520</int>
          </void>
         </void>
        </object>
       </void>
       <void property="excursion">
        <long>272493</long>
       </void>
       <void property="longHalfAxis">
        <long>164730843</long>
       </void>
       <void property="newOrderParameter">
        <long>-1000000000</long>
       </void>
       <void property="newOrientation">
        <long>-1000000000</long>
       </void>
       <void property="orderParameter">
        <long>-1000000000</long>
       </void>
       <void property="orientation">
        <long>35135169</long>
       </void>
      </object>
     </void>
    </void>
   </object>
  </void>
 </object>
</java>
